jupyter_turtle/__init__.py
jupyter_turtle/turtle.png
jupyter_turtle/turtle.py
jupyter_turtle-1.0.3.dist-info/licenses/LICENSE
jupyter_turtle-1.0.3.dist-info/METADATA
jupyter_turtle-1.0.3.dist-info/WHEEL
jupyter_turtle-1.0.3.dist-info/top_level.txt
jupyter_turtle-1.0.3.dist-info/RECORD
