Metadata-Version: 2.4
Name: jupyter-turtle
Version: 1.0.3
Summary: Simplified Turtle graphics for the Jupyter Notebook
Author-email: Mike Matera <michael.matera@cabrillo.edu>
License-Expression: MIT
Project-URL: Homepage, https://github.com/mike-matera/jupyter-turtle
Project-URL: Issues, https://github.com/mike-matera/jupyter-turtle/issues
Classifier: Programming Language :: Python :: 3
Classifier: Operating System :: OS Independent
Requires-Python: >=3.9
License-File: LICENSE
Requires-Dist: ipycanvas
Requires-Dist: jupyterlab
Dynamic: license-file
